{
  "_meta": {
    "language": "en",
    "version": 1,
    "author": "Metal Pod Team"
  },

  "menu.title": "Metal Pod",
  "menu.subtitle": "Heavy Metal Hovercraft Racing",
  "menu.play": "Play",
  "menu.continue": "Continue",
  "menu.new_game": "New Game",
  "menu.new_game_confirm": "Start a new game? This will reset your progress.",
  "menu.confirm_yes": "Yes",
  "menu.confirm_no": "No",
  "menu.settings": "Settings",
  "menu.quit": "Quit",

  "workshop.title": "Workshop",
  "workshop.courses": "Courses",
  "workshop.upgrades": "Upgrades",
  "workshop.customize": "Customize",
  "workshop.back": "Back",
  "workshop.launch": "Launch",

  "course.locked": "Locked",
  "course.locked_requires": "Requires: {0}",
  "course.requires_medals": "Requires {0} medals",
  "course.best_time": "Best: {0}",
  "course.no_time": "No time set",
  "course.no_time_short": "--:--.--",
  "course.no_course": "No Course",
  "course.no_hazards": "No hazards listed.",
  "course.hazard_bullet": "• {0}",
  "course.medal_gold": "Gold",
  "course.medal_silver": "Silver",
  "course.medal_bronze": "Bronze",
  "course.medal_none": "No Medal",
  "course.checkpoint": "Checkpoint {0}/{1}",
  "course.difficulty": "Difficulty: {0}",
  "course.difficulty_easy": "Easy",
  "course.difficulty_medium": "Medium",
  "course.difficulty_hard": "Hard",
  "course.lava1": "Inferno Gate",
  "course.lava2": "Molten Ridge",
  "course.lava3": "Magma Canyon",
  "course.ice1": "Frozen Pass",
  "course.ice2": "Glacial Ravine",
  "course.ice3": "Arctic Storm",
  "course.toxic1": "Rust Valley",
  "course.toxic2": "Chemical Plant",
  "course.toxic3": "Biohazard Core",
  "course.test": "Test Course",

  "env.lava": "Lava Zone",
  "env.ice": "Ice Zone",
  "env.toxic": "Toxic Zone",

  "hud.speed": "{0} km/h",
  "hud.speed_numeric": "{0:000}",
  "hud.health": "Health",
  "hud.shield": "Shield",
  "hud.boost": "Boost",
  "hud.timer": "{0}",
  "hud.lap": "Lap {0}/{1}",
  "hud.ready": "Ready",

  "countdown.3": "3",
  "countdown.2": "2",
  "countdown.1": "1",
  "countdown.go": "GO!",
  "countdown.go_short": "GO",

  "results.title": "Race Complete!",
  "results.failed": "Race Failed",
  "results.time": "Time: {0}",
  "results.best_time": "Best: {0}",
  "results.new_record": "New Record!",
  "results.medal_earned": "{0} Medal!",
  "results.medal_earned_announce": "{0} medal earned.",
  "results.bolts_earned": "+{0} Bolts",
  "results.base_bolts": "Base: {0}",
  "results.bonus_bolts": "Bonus: {0}",
  "results.total_bolts": "Total: {0}",
  "results.collectibles": "{0}/{1}",
  "results.health_remaining": "{0}%",
  "results.retry": "Retry",
  "results.next": "Next Course",
  "results.workshop_return": "Workshop",
  "results.zero": "0",

  "upgrade.speed": "Speed",
  "upgrade.armor": "Armor",
  "upgrade.handling": "Handling",
  "upgrade.boost": "Boost",
  "upgrade.level": "Level {0}/{1}",
  "upgrade.level_short": "Lv {0}",
  "upgrade.max": "MAX",
  "upgrade.max_level": "Max Level",
  "upgrade.cost": "{0} Bolts",
  "upgrade.purchase": "Upgrade",
  "upgrade.insufficient": "Not enough bolts",
  "upgrade.stat_current": "Current: {0}",
  "upgrade.stat_next": "Next: {0}",
  "upgrade.stat_current_mult": "Current: x{0:0.00}",
  "upgrade.stat_next_mult": "Next: x{0:0.00}",
  "upgrade.placeholder": "--",

  "cosmetic.colors": "Colors",
  "cosmetic.decals": "Decals",
  "cosmetic.parts": "Parts",
  "cosmetic.owned": "Owned",
  "cosmetic.equipped": "Equipped",
  "cosmetic.locked": "Locked — {0} Bolts",
  "cosmetic.locked_price": "Locked. Price: {0} bolts.",
  "cosmetic.purchase": "Buy",
  "cosmetic.equip": "Equip",
  "cosmetic.price": "{0}",
  "cosmetic.placeholder": "--",

  "pause.title": "Paused",
  "pause.resume": "Resume",
  "pause.restart": "Restart",
  "pause.settings": "Settings",
  "pause.quit": "Quit to Menu",

  "settings.title": "Settings",
  "settings.master_volume": "Master Volume",
  "settings.music_volume": "Music",
  "settings.sfx_volume": "SFX",
  "settings.tilt_sensitivity": "Tilt Sensitivity",
  "settings.tilt_sensitivity_value": "{0:F1}x",
  "settings.invert_tilt": "Invert Tilt",
  "settings.haptics": "Haptic Feedback",
  "settings.language": "Language",
  "settings.quality": "Graphics Quality",
  "settings.quality_low": "Low",
  "settings.quality_medium": "Medium",
  "settings.quality_high": "High",
  "settings.back": "Back",

  "loading.loading": "Loading...",
  "loading.loading_progress": "Loading... {0}%",
  "loading.tip_prefix": "Tip: ",
  "loading.tip.1": "Use boost to break through ice walls!",
  "loading.tip.2": "Shield regenerates after a few seconds of safety.",
  "loading.tip.3": "Collect currency to upgrade your pod in the workshop.",
  "loading.tip.4": "Gold medals require mastering every shortcut.",
  "loading.tip.5": "Watch for ground shadows. Something is falling!",
  "loading.tip.6": "The avalanche waits for no one. Keep moving!",
  "loading.tip.7": "Upgrade handling to tame ice patches.",
  "loading.tip.8": "Electric fences stun your controls briefly.",

  "currency.bolts": "{0} Bolts",
  "currency.bolts_short": "{0}",

  "unlock.title": "Course Unlocked!",
  "unlock.message": "{0} is now available!",
  "unlock.inline": "UNLOCKED: {0}",

  "tutorial.welcome": "Welcome to Metal Pod!",
  "tutorial.steer": "Tilt your device to steer",
  "tutorial.speed": "You automatically accelerate forward",
  "tutorial.boost": "Tap the right side to boost!",
  "tutorial.brake": "Tap the left side to brake",
  "tutorial.health": "Watch your health bar - avoid hazards!",
  "tutorial.hazard": "Hazards deal different types of damage",
  "tutorial.checkpoint": "Pass through checkpoints to save progress",
  "tutorial.collectible": "Collect bolts to earn currency",
  "tutorial.finish": "Cross the finish line to complete the course!",
  "tutorial.skip": "Skip Tutorial",
  "tutorial.next": "Next",
  "tutorial.got_it": "Got it!",
  "tutorial.workshop_welcome": "Welcome to the Workshop!",
  "tutorial.workshop_tabs": "Use the tabs to browse courses, upgrades, and cosmetics",
  "tutorial.workshop_launch": "Select a course and tap Launch to race!",
  "tutorial.tap_to_continue": "Tap to continue.",
  "tutorial.sequence_first_play": "First Time Playing",
  "tutorial.sequence_workshop_intro": "Workshop Introduction",

  "tutorial.step.welcome.title": "WELCOME TO METAL POD",
  "tutorial.step.welcome.subtitle": "Let's learn the basics. Tap to continue.",
  "tutorial.step.steering.title": "TILT TO STEER",
  "tutorial.step.steering.subtitle": "Tilt your device left and right to turn.",
  "tutorial.step.speed.title": "YOU'RE MOVING!",
  "tutorial.step.speed.subtitle": "Your pod accelerates automatically. Watch your speed on the HUD.",
  "tutorial.step.boost.title": "TAP TO BOOST",
  "tutorial.step.boost.subtitle": "Tap the right side of the screen for a speed burst!",
  "tutorial.step.brake.title": "HOLD TO BRAKE",
  "tutorial.step.brake.subtitle": "Hold the left side of the screen to slow down.",
  "tutorial.step.health.title": "WATCH YOUR HEALTH",
  "tutorial.step.health.subtitle": "Your shield (blue) absorbs damage first. Health (red) is below it. Avoid hazards!",
  "tutorial.step.damage_warning.title": "HAZARD AHEAD!",
  "tutorial.step.damage_warning.subtitle": "Lava flows deal damage. Steer clear or boost past them!",
  "tutorial.step.checkpoint.title": "CHECKPOINT!",
  "tutorial.step.checkpoint.subtitle": "If you're destroyed, you'll respawn here.",
  "tutorial.step.collectible.title": "GRAB COLLECTIBLES",
  "tutorial.step.collectible.subtitle": "Floating pickups give bonus currency and health.",
  "tutorial.step.finish_line.title": "REACH THE FINISH!",
  "tutorial.step.finish_line.subtitle": "Race to the end. Faster times earn better medals!",
  "tutorial.step.workshop_welcome.title": "THE WORKSHOP",
  "tutorial.step.workshop_welcome.subtitle": "This is your base. Upgrade your pod, customize it, and pick your next course.",
  "tutorial.step.workshop_upgrades.title": "UPGRADES",
  "tutorial.step.workshop_upgrades.subtitle": "Spend currency to improve Speed, Handling, Shields, and Boost.",
  "tutorial.step.workshop_courses.title": "CHOOSE A COURSE",
  "tutorial.step.workshop_courses.subtitle": "Tap Courses to pick your next challenge. Earn medals to unlock more!",

  "accessibility.play_button": "Play. Double tap to enter the Workshop.",
  "accessibility.settings_button": "Settings. Double tap to open settings.",
  "accessibility.quit_button": "Quit. Double tap to exit the game.",
  "accessibility.courses_tab": "Courses tab. Double tap to browse race courses.",
  "accessibility.upgrades_tab": "Upgrades tab. Double tap to upgrade your hovercraft.",
  "accessibility.customize_tab": "Customize tab. Double tap to customize appearance.",
  "accessibility.launch_button": "Launch race. Double tap to start the selected course.",
  "accessibility.back_button": "Back. Double tap to return to the previous screen.",
  "accessibility.speed_display": "Current speed: {0} kilometers per hour",
  "accessibility.health_bar": "Health: {0} percent",
  "accessibility.shield_bar": "Shield: {0} percent",
  "accessibility.boost_bar": "Boost: {0} percent",
  "accessibility.timer_display": "Race time: {0}",
  "accessibility.checkpoint_display": "Checkpoint {0} of {1}",
  "accessibility.currency_display": "Bolts: {0}",
  "accessibility.course_card": "{0}. {1} environment. Best time: {2}. Medal: {3}.",
  "accessibility.locked_course": "{0}. Locked. Requires: {1}.",
  "accessibility.upgrade_category": "{0}. Level {1} of 5. Cost to upgrade: {2} bolts.",
  "accessibility.upgrade_maxed": "{0}. Maximum level reached.",
  "accessibility.purchase_upgrade": "Purchase {0} upgrade for {1} bolts. Double tap to confirm.",
  "accessibility.cosmetic_item": "{0}. {1}.",
  "accessibility.cosmetic_locked": "{0}. Locked. Price: {1} bolts.",
  "accessibility.cosmetic_equipped": "{0}. Currently equipped.",
  "accessibility.race_complete": "Race complete. Time: {0}. Medal: {1}. Bolts earned: {2}.",
  "accessibility.new_record": "New record. Previous best: {0}.",
  "accessibility.gold_medal": "Gold medal",
  "accessibility.silver_medal": "Silver medal",
  "accessibility.bronze_medal": "Bronze medal",
  "accessibility.no_medal": "No medal",
  "accessibility.countdown_announce": "{0}",
  "accessibility.checkpoint_reached": "Checkpoint reached. {0} of {1}.",
  "accessibility.damage_taken": "Damage taken. Health at {0} percent.",
  "accessibility.medal_earned": "{0} earned.",
  "accessibility.course_unlocked": "New course unlocked: {0}."
}
